dbms5thsem.py
dbms5thsem-0.0.3.dist-info/LICENSE
dbms5thsem-0.0.3.dist-info/METADATA
dbms5thsem-0.0.3.dist-info/WHEEL
dbms5thsem-0.0.3.dist-info/top_level.txt
dbms5thsem-0.0.3.dist-info/RECORD
