Metadata-Version: 2.1
Name: dbms5thsem
Version: 0.0.3
Summary: DBMS lab programs definitions
Author: aiml department
Author-email: aiml@gmail.com
License: MIT
Keywords: DBMS lab
Classifier: Programming Language :: Python :: 3
Classifier: License :: OSI Approved :: MIT License
Classifier: Operating System :: OS Independent
Requires-Python: >=3.7
License-File: LICENSE
